._.DS_Store
COPYING
INSTALL
MANIFEST.in
README
TODO
ez_setup.py
setup.py
Chiplotle.egg-info/PKG-INFO
Chiplotle.egg-info/SOURCES.txt
Chiplotle.egg-info/dependency_links.txt
Chiplotle.egg-info/entry_points.txt
Chiplotle.egg-info/requires.txt
Chiplotle.egg-info/top_level.txt
chiplotle/__init__.py
chiplotle/core/__init__.py
chiplotle/core/errors.py
chiplotle/core/visitor.py
chiplotle/core/cfg/__init__.py
chiplotle/core/cfg/_run_chiplotle.py
chiplotle/core/cfg/_run_chiplotle_virtual.py
chiplotle/core/cfg/cfg.py
chiplotle/core/cfg/get_config_value.py
chiplotle/core/cfg/initialize_files.py
chiplotle/core/cfg/read_config_file.py
chiplotle/core/cfg/write_config_file.py
chiplotle/core/cfg/write_log_file.py
chiplotle/core/devscripts/replace_in_files.py
chiplotle/core/imports/__init__.py
chiplotle/core/imports/get_functions_in_module.py
chiplotle/core/imports/package_import.py
chiplotle/core/imports/remove_modules_from_namespace.py
chiplotle/core/interfaces/__init__.py
chiplotle/core/interfaces/formatdecorator.py
chiplotle/core/interfaces/interface.py
chiplotle/core/interfaces/margins/__init__.py
chiplotle/core/interfaces/margins/interface.py
chiplotle/core/interfaces/parentage/__init__.py
chiplotle/core/interfaces/parentage/interface.py
chiplotle/documentation/Makefile
chiplotle/documentation/conf.py
chiplotle/documentation/index.rst
chiplotle/documentation/install.rst
chiplotle/documentation/_themes/chiplotle/layout.html
chiplotle/documentation/_themes/chiplotle/theme.conf
chiplotle/documentation/_themes/chiplotle/static/chiplotle_logo_2.png
chiplotle/documentation/_themes/chiplotle/static/default.css_t
chiplotle/documentation/_themes/chiplotle/static/ga-1.js
chiplotle/documentation/_themes/chiplotle/static/ga-2.js
chiplotle/documentation/_themes/chiplotle/static/ga.js
chiplotle/documentation/chapters/about/index.rst
chiplotle/documentation/chapters/api/geometry.rst
chiplotle/documentation/chapters/api/hpgl.rst
chiplotle/documentation/chapters/api/index.rst
chiplotle/documentation/chapters/api/plotters.rst
chiplotle/documentation/chapters/api/tools.rst
chiplotle/documentation/chapters/configuration/index.rst
chiplotle/documentation/chapters/contributors/index.rst
