Metadata-Version: 1.0
Name: Chiplotle
Version: 0.4.1
Summary: Chiplotle is an HPGL Python API.
Home-page: http://music.columbia.edu/cmc/chiplotle
Author: Víctor Adán and Douglas Repetto
Author-email: chiplotle@music.columbia.edu
License: GPL
Keywords: vector graphics hpgl plotter plot pen
Platform: UNKNOWN
